{
  "project_info": {
    "project_number": "306823952848",
    "project_id": "flutter-rent-house-3f415",
    "storage_bucket": "flutter-rent-house-3f415.appspot.com"
  },
  "client": [
    {
      "client_info": {
        "mobilesdk_app_id": "1:306823952848:android:2add5f6d60f9e3a8ef61d5",
        "android_client_info": {
          "package_name": "com.builtlab.smartrent"
        }
      },
      "oauth_client": [],
      "api_key": [
        {
          "current_key": "AIzaSyBC5XsEcx90TU2pWq2iTPCBN58dTKUmKSM"
        }
      ],
      "services": {
        "appinvite_service": {
          "other_platform_oauth_client": []
        }
      }
    }
  ],
  "configuration_version": "1"
}